datagrunt/__init__.py
datagrunt/core/__init__.py
datagrunt/core/ai/__init__.py
datagrunt/core/ai/engines.py
datagrunt/core/ai/factories.py
datagrunt/core/ai/prompts.py
datagrunt/core/csv_io/__init__.py
datagrunt/core/csv_io/csvcomponents.py
datagrunt/core/csv_io/engines.py
datagrunt/core/csv_io/factories.py
datagrunt/core/databases/__init__.py
datagrunt/core/databases/databases.py
datagrunt/core/file_io/__init__.py
datagrunt/core/file_io/fileproperties.py
datagrunt/csv_api/__init__.py
datagrunt/csv_api/csvai.py
datagrunt/csv_api/csvreader.py
datagrunt/csv_api/csvwriter.py
datagrunt-2.1.2.dist-info/licenses/LICENSE
datagrunt-2.1.2.dist-info/METADATA
datagrunt-2.1.2.dist-info/WHEEL
datagrunt-2.1.2.dist-info/top_level.txt
datagrunt-2.1.2.dist-info/RECORD
