Metadata-Version: 2.4
Name: datagrunt
Version: 2.1.2
Summary: Read CSV files and convert to other file formats easily
Author-email: Martin Graham <datagrunt@datagrunt.io>
License: MIT License
Project-URL: Homepage, https://pmgraham.github.io/datagrunt
Project-URL: Bug Tracker, https://github.com/pmgraham/datagrunt/issues
Project-URL: Documentation, https://pmgraham.github.io/datagrunt
Project-URL: Source Code, https://github.com/pmgraham/datagrunt
Keywords: csv,data,duckdb,polars,pyarrow,xlsx,delimiter,ai,gemini
Classifier: License :: OSI Approved :: MIT License
Classifier: Programming Language :: Python
Classifier: Programming Language :: Python :: 3
Classifier: Programming Language :: Python :: 3.10
Classifier: Programming Language :: Python :: 3.11
Classifier: Intended Audience :: Developers
Classifier: Topic :: Software Development :: Libraries :: Python Modules
Requires-Python: >=3.10
License-File: LICENSE
Requires-Dist: duckdb>=1.1.0
Requires-Dist: polars>=1.7.1
Requires-Dist: pyarrow>=17.0.0
Requires-Dist: XlsxWriter>=3.2.0
Requires-Dist: google-genai>=1.25.0
Provides-Extra: dev
Requires-Dist: pytest>=8.3.4; extra == "dev"
Requires-Dist: pytest-cov>=6.0.0; extra == "dev"
Requires-Dist: ruff>=0.5.5; extra == "dev"
Requires-Dist: bumpver>=2024.1130; extra == "dev"
Requires-Dist: fastexcel>=0.13.0; extra == "dev"
Dynamic: license-file
